aiodoc/__init__.py
aiodoc/aws.py
aiodoc/base.py
aiodoc/file.py
aiodoc/file_factory.py
aiodoc/ftp.py
aiodoc/gcp.py
aiodoc/http.py
aiodoc/memcached.py
aiodoc/minio.py
aiodoc/redis.py
aiodoc-0.1.2.dist-info/METADATA
aiodoc-0.1.2.dist-info/WHEEL
aiodoc-0.1.2.dist-info/RECORD
