Metadata-Version: 2.1
Name: aiodoc
Version: 0.1.2
Summary: This library allows you to retrieve BytesIO objects from various sources asynchronously. Whether you're dealing with cloud storage, HTTP endpoints, FTP servers, or local files.
Author: Chris
Author-email: goabonga@pm.me
Requires-Python: >=3.12,<4.0
Classifier: Programming Language :: Python :: 3
Classifier: Programming Language :: Python :: 3.12
Classifier: Programming Language :: Python :: 3.13
